nasap_net/__init__.py
nasap_net/assembly_enumeration/__init__.py
nasap_net/assembly_enumeration/conftest.py
nasap_net/assembly_enumeration/core.py
nasap_net/assembly_enumeration/lib/__init__.py
nasap_net/assembly_enumeration/lib/capping.py
nasap_net/assembly_enumeration/lib/fragment_enumeration/__init__.py
nasap_net/assembly_enumeration/lib/fragment_enumeration/core.py
nasap_net/assembly_enumeration/lib/fragment_enumeration/lib/__init__.py
nasap_net/assembly_enumeration/lib/fragment_enumeration/lib/fragment_growth.py
nasap_net/assembly_enumeration/lib/fragment_enumeration/lib/is_new.py
nasap_net/assembly_enumeration/lib/fragment_enumeration/lib/key.py
nasap_net/assembly_enumeration/lib/fragment_enumeration/lib/starting_fragments.py
nasap_net/assembly_enumeration/lib/fragment_enumeration/lib/sub_fragment.py
nasap_net/assembly_enumeration/lib/fragment_enumeration/lib/symmetry_operation.py
nasap_net/assembly_enumeration/lib/fragment_enumeration/lib/unique.py
nasap_net/assembly_enumeration/lib/fragment_enumeration/models/__init__.py
nasap_net/assembly_enumeration/lib/fragment_enumeration/models/fragment.py
nasap_net/assembly_enumeration/lib/fragment_enumeration/models/growing_step.py
nasap_net/assembly_enumeration/lib/fragment_enumeration/models/light_bond.py
nasap_net/assembly_enumeration/lib/fragment_enumeration/models/template_assembly.py
nasap_net/assembly_enumeration/lib/fragment_enumeration/tests/__init__.py
nasap_net/assembly_enumeration/lib/fragment_enumeration/tests/test_core.py
nasap_net/assembly_enumeration/lib/symmetry_operation.py
nasap_net/assembly_enumeration/tests/__init__.py
nasap_net/assembly_enumeration/tests/test_core.py
nasap_net/assembly_equivalence/__init__.py
nasap_net/assembly_equivalence/core.py
nasap_net/assembly_equivalence/search.py
nasap_net/assembly_equivalence/signature.py
nasap_net/assembly_equivalence/tests/__init__.py
nasap_net/assembly_equivalence/tests/test_isomorphic_assembly_search.py
nasap_net/assembly_equivalence/unique.py
nasap_net-1.0.1.dist-info/METADATA
nasap_net-1.0.1.dist-info/WHEEL
nasap_net-1.0.1.dist-info/licenses/LICENSE
nasap_net-1.0.1.dist-info/RECORD
