Metadata-Version: 2.4
Name: nasap-net
Version: 1.0.1
Summary: Automated reaction network generator for NASAP (Numerical Analysis of Self-Assembly Process)
License: MIT
License-File: LICENSE
Author: takeuchi-sci
Author-email: 142223934+takeuchi-sci@users.noreply.github.com
Requires-Python: >=3.12,<4.0
Classifier: License :: OSI Approved :: MIT License
Classifier: Programming Language :: Python :: 3
Classifier: Programming Language :: Python :: 3.12
Classifier: Programming Language :: Python :: 3.13
Classifier: Programming Language :: Python :: 3.14
Requires-Dist: bidict (>=0.23.1,<0.24.0)
Requires-Dist: frozendict (>=2.4.6,<3.0.0)
Requires-Dist: igraph (>=1.0.0,<2.0.0)
Requires-Dist: pandas (>=2.2.2,<3.0.0)
Requires-Dist: pyyaml (>=6.0.2,<7.0.0)
